nvidia_cutlass_dsl.pth
nvidia_cutlass_dsl/LICENSE
nvidia_cutlass_dsl/lib/libcuda_dialect_runtime.so
nvidia_cutlass_dsl/lib/libcuda_dialect_runtime_static.a
nvidia_cutlass_dsl/python_packages/cutlass/__init__.py
nvidia_cutlass_dsl/python_packages/cutlass/impl_utils.py
nvidia_cutlass_dsl/python_packages/cutlass/torch.py
nvidia_cutlass_dsl/python_packages/cutlass/_mlir/execution_engine.py
nvidia_cutlass_dsl/python_packages/cutlass/_mlir/ir.py
nvidia_cutlass_dsl/python_packages/cutlass/_mlir/passmanager.py
nvidia_cutlass_dsl/python_packages/cutlass/_mlir/rewrite.py
nvidia_cutlass_dsl/python_packages/cutlass/_mlir/_mlir_libs/__init__.py
nvidia_cutlass_dsl/python_packages/cutlass/_mlir/_mlir_libs/_cutlass_ir.cpython-311-x86_64-linux-gnu.so
nvidia_cutlass_dsl/python_packages/cutlass/_mlir/_mlir_libs/_site_initialize_0.cpython-311-x86_64-linux-gnu.so
nvidia_cutlass_dsl/python_packages/cutlass/_mlir/_mlir_libs/_cutlass_ir/_mlirExecutionEngine.pyi
nvidia_cutlass_dsl/python_packages/cutlass/_mlir/_mlir_libs/_cutlass_ir/_mlir/__init__.pyi
nvidia_cutlass_dsl/python_packages/cutlass/_mlir/_mlir_libs/_cutlass_ir/_mlir/ir.pyi
nvidia_cutlass_dsl/python_packages/cutlass/_mlir/_mlir_libs/_cutlass_ir/_mlir/passmanager.pyi
nvidia_cutlass_dsl/python_packages/cutlass/_mlir/dialects/_arith_enum_gen.py
nvidia_cutlass_dsl/python_packages/cutlass/_mlir/dialects/_arith_ops_gen.py
nvidia_cutlass_dsl/python_packages/cutlass/_mlir/dialects/_builtin_ops_gen.py
nvidia_cutlass_dsl/python_packages/cutlass/_mlir/dialects/_cf_ops_gen.py
nvidia_cutlass_dsl/python_packages/cutlass/_mlir/dialects/_cuda_enum_gen.py
nvidia_cutlass_dsl/python_packages/cutlass/_mlir/dialects/_cuda_ops_gen.py
nvidia_cutlass_dsl/python_packages/cutlass/_mlir/dialects/_cute_enum_gen.py
nvidia_cutlass_dsl/python_packages/cutlass/_mlir/dialects/_cute_nvgpu_enum_gen.py
nvidia_cutlass_dsl/python_packages/cutlass/_mlir/dialects/_cute_nvgpu_ops_gen.py
nvidia_cutlass_dsl-4.3.5.dist-info/METADATA
nvidia_cutlass_dsl-4.3.5.dist-info/WHEEL
nvidia_cutlass_dsl-4.3.5.dist-info/top_level.txt
nvidia_cutlass_dsl-4.3.5.dist-info/RECORD
nvidia_cutlass_dsl-4.3.5.dist-info/licenses/LICENSE
