Metadata-Version: 2.4
Name: nvidia-cutlass-dsl
Version: 4.3.5
Summary: NVIDIA CUTLASS Python DSL
Author: NVIDIA Corporation
Project-URL: Documentation, https://github.com/NVIDIA/cutlass
Project-URL: Repository, https://github.com/NVIDIA/cutlass
Project-URL: Issues, https://github.com/NVIDIA/cutlass/issues
Project-URL: License, https://docs.nvidia.com/cutlass/media/docs/pythonDSL/license.html
Classifier: Development Status :: 4 - Beta
Classifier: Environment :: GPU :: NVIDIA CUDA :: 12
Classifier: License :: Other/Proprietary License
Classifier: Operating System :: POSIX :: Linux
Classifier: Programming Language :: Python :: 3 :: Only
Classifier: Programming Language :: Python :: 3.10
Classifier: Programming Language :: Python :: 3.11
Classifier: Programming Language :: Python :: 3.12
Classifier: Programming Language :: Python :: 3.13
Classifier: Programming Language :: Python :: Implementation :: CPython
Requires-Python: >=3.10
License-File: LICENSE
Requires-Dist: numpy
Requires-Dist: typing-extensions
Requires-Dist: cuda-python>=12.8
Dynamic: license-file
